streamlit_theme_provider/__init__.py
streamlit_theme_provider/frontend/index.html
streamlit_theme_provider/frontend/main.js
streamlit_theme_provider/frontend/streamlit-component-lib.js
streamlit_theme_provider/frontend/style.css
streamlit_theme_provider-0.1.0.dist-info/LICENSE
streamlit_theme_provider-0.1.0.dist-info/METADATA
streamlit_theme_provider-0.1.0.dist-info/WHEEL
streamlit_theme_provider-0.1.0.dist-info/top_level.txt
streamlit_theme_provider-0.1.0.dist-info/RECORD
