Metadata-Version: 2.1
Name: streamlit-theme-provider
Version: 0.1.0
Summary: Streamlit component that allows you to get the current theme.
Author: Rishabh Indoria
Author-email: rishabhindoria2203@gmail.com
Requires-Python: >=3.7
License-File: LICENSE
Requires-Dist: streamlit>=1.2
Requires-Dist: jinja2
